witlab/__init__.py
witlab/data/datasets/gw/subjects/NAP_001/functional/BOLD_rsfMRI.mat
witlab/data/datasets/gw/subjects/NAP_001/structural/DTI_CM.mat
witlab/data/datasets/gw/subjects/NAP_001/structural/DTI_LEN.mat
witlab/data/datasets/gw/subjects/NAP_002/functional/BOLD_rsfMRI.mat
witlab/data/datasets/gw/subjects/NAP_002/structural/DTI_CM.mat
witlab/data/datasets/gw/subjects/NAP_002/structural/DTI_LEN.mat
witlab/data/datasets/gw/subjects/NAP_007/functional/BOLD_rsfMRI.mat
witlab/data/datasets/gw/subjects/NAP_007/structural/DTI_CM.mat
witlab/data/datasets/gw/subjects/NAP_007/structural/DTI_LEN.mat
witlab/data/datasets/gw/subjects/NAP_009/functional/BOLD_rsfMRI.mat
witlab/data/datasets/gw/subjects/NAP_009/structural/DTI_CM.mat
witlab/data/datasets/gw/subjects/NAP_009/structural/DTI_LEN.mat
witlab/data/datasets/gw/subjects/NAP_013/functional/BOLD_rsfMRI.mat
witlab/data/datasets/gw/subjects/NAP_013/structural/DTI_CM.mat
witlab/data/datasets/gw/subjects/NAP_013/structural/DTI_LEN.mat
witlab/data/datasets/hcp/subjects/101309/functional/TC_rsfMRI_REST1_LR.mat
witlab/data/datasets/hcp/subjects/101309/structural/DTI_CM.mat
witlab/data/datasets/hcp/subjects/101309/structural/DTI_LEN.mat
witlab/data/datasets/hcp/subjects/101309/structural/nvoxel.txt
witlab/data/datasets/hcp/subjects/101309/structural/waytotal.txt
witlab/data/datasets/hcp/subjects/102311/functional/TC_rsfMRI_REST1_LR.mat
witlab/data/datasets/hcp/subjects/102311/structural/DTI_CM.mat
witlab/data/datasets/hcp/subjects/102311/structural/DTI_LEN.mat
witlab/data/datasets/hcp/subjects/102311/structural/nvoxel.txt
witlab/data/datasets/hcp/subjects/102311/structural/waytotal.txt
witlab/data/datasets/hcp/subjects/102816/functional/TC_rsfMRI_REST1_LR.mat
witlab/data/datasets/hcp/subjects/102816/structural/DTI_CM.mat
witlab/data/datasets/hcp/subjects/102816/structural/DTI_LEN.mat
witlab/data/datasets/hcp/subjects/102816/structural/nvoxel.txt
witlab/data/datasets/hcp/subjects/102816/structural/waytotal.txt
witlab-0.0.2.dist-info/LICENSE
witlab-0.0.2.dist-info/METADATA
witlab-0.0.2.dist-info/WHEEL
witlab-0.0.2.dist-info/top_level.txt
witlab-0.0.2.dist-info/RECORD
